syzygy_docs_themes/__init__.py
syzygy_docs_themes/caperea/__init__.py
syzygy_docs_themes/caperea/theme.conf
syzygy_docs_themes/caperea/static/caperea-docs.css
syzygy_docs_themes/kogia/__init__.py
syzygy_docs_themes/kogia/theme.conf
syzygy_docs_themes/kogia/static/kogia-docs.css
syzygy_docs_themes/stenella/__init__.py
syzygy_docs_themes/stenella/theme.conf
syzygy_docs_themes/stenella/static/stenella-docs.css
syzygy_docs_themes/syzygy/__init__.py
syzygy_docs_themes/syzygy/globaltoc.html
syzygy_docs_themes/syzygy/layout.html
syzygy_docs_themes/syzygy/localtoc.html
syzygy_docs_themes/syzygy/relations.html
syzygy_docs_themes/syzygy/theme.conf
syzygy_docs_themes/syzygy/static/syzygy-docs.css
syzygy_docs_themes/syzygy/static/syzygy-docs.js
syzygy_docs_themes/syzygy/static/assets/vendor/fontawesome-free/LICENSE.txt
syzygy_docs_themes/syzygy/static/assets/vendor/fontawesome-free/webfonts/fa-brands-400.woff
syzygy_docs_themes/syzygy/static/assets/vendor/fontawesome-free/webfonts/fa-brands-400.woff2
syzygy_docs_themes/syzygy/static/assets/vendor/fontawesome-free/webfonts/fa-solid-900.woff
syzygy_docs_themes/syzygy/static/assets/vendor/fontawesome-free/webfonts/fa-solid-900.woff2
syzygy_docs_themes/syzygy/static/assets/vendor/noto-sans-jp/OFL.txt
syzygy_docs_themes/syzygy/static/assets/vendor/noto-sans-jp/noto-sans-jp-v25-latin-300.woff
syzygy_docs_themes/syzygy/static/assets/vendor/noto-sans-jp/noto-sans-jp-v25-latin-300.woff2
syzygy_docs_themes/syzygy/static/assets/vendor/noto-sans-jp/noto-sans-jp-v25-latin-500.woff
syzygy_docs_themes/syzygy/static/assets/vendor/noto-sans-jp/noto-sans-jp-v25-latin-500.woff2
syzygy_docs_themes/syzygy/static/assets/vendor/noto-sans-jp/noto-sans-jp-v25-latin-700.woff
syzygy_docs_themes/syzygy/static/assets/vendor/noto-sans-jp/noto-sans-jp-v25-latin-700.woff2
syzygy_docs_themes/syzygy/static/assets/vendor/noto-sans-jp/noto-sans-jp-v25-latin-regular.woff
syzygy_docs_themes-0.1.0.dev1.dist-info/LICENSE
syzygy_docs_themes-0.1.0.dev1.dist-info/METADATA
syzygy_docs_themes-0.1.0.dev1.dist-info/NOTICE
syzygy_docs_themes-0.1.0.dev1.dist-info/WHEEL
syzygy_docs_themes-0.1.0.dev1.dist-info/entry_points.txt
syzygy_docs_themes-0.1.0.dev1.dist-info/top_level.txt
syzygy_docs_themes-0.1.0.dev1.dist-info/RECORD
