Metadata-Version: 2.1
Name: syzygy-docs-themes
Version: 0.1.0.dev1
Summary: Sphinx themes for the documentation of Kogia, Caperea and Stenella.
Home-page: https://pascalpepe.gitlab.io/syzygy-docs-themes
Author: Pascal Pepe
Author-email: contact@pascalpepe.fr
License: Apache-2.0
Project-URL: Documentation, https://pascalpepe.gitlab.io/syzygy-docs-themes
Project-URL: Source code, https://gitlab.com/pascalpepe/syzygy-docs-themes
Project-URL: Issue tracker, https://gitlab.com/pascalpepe/syzygy-docs-themes/issues
Keywords: sphinx docs theme kogia caperea stenella
Platform: UNKNOWN
Classifier: Development Status :: 1 - Planning
Classifier: Environment :: Web Environment
Classifier: Framework :: Sphinx
Classifier: Framework :: Sphinx :: Theme
Classifier: Intended Audience :: Education
Classifier: Intended Audience :: Developers
Classifier: Intended Audience :: Science/Research
Classifier: Intended Audience :: System Administrators
Classifier: License :: OSI Approved :: Apache Software License
Classifier: Operating System :: OS Independent
Classifier: Programming Language :: Python
Classifier: Programming Language :: Python :: 3
Classifier: Programming Language :: Python :: 3 :: Only
Classifier: Programming Language :: Python :: 3.5
Classifier: Programming Language :: Python :: 3.6
Classifier: Programming Language :: Python :: 3.7
Classifier: Programming Language :: Python :: 3.8
Classifier: Topic :: Documentation
Classifier: Topic :: Documentation :: Sphinx
Classifier: Topic :: Internet
Classifier: Topic :: Internet :: WWW/HTTP
Classifier: Topic :: Internet :: WWW/HTTP :: Site Management
Classifier: Topic :: Software Development
Classifier: Topic :: Software Development :: Documentation
